xy_work/ModuleData.py
xy_work/Work.py
xy_work/__init__.py
xy_work/Settings/Settings.py
xy_work/Settings/__init__.py
xy_work/Settings/Section/Project.py
xy_work/Settings/Section/Runner.py
xy_work/Settings/Section/__init__.py
xy_work/data/template/config/xy_work_toml.template
xy_work/data/template/runner/runner_py.template
xy_work/execute/Main.py
xy_work/execute/__init__.py
xy_work-1.0.16.dist-info/LICENSE
xy_work-1.0.16.dist-info/METADATA
xy_work-1.0.16.dist-info/WHEEL
xy_work-1.0.16.dist-info/entry_points.txt
xy_work-1.0.16.dist-info/top_level.txt
xy_work-1.0.16.dist-info/RECORD
