Metadata-Version: 2.1
Name: xy_work
Version: 1.0.16
Summary: xy_work 模块
Author-email: 余洋 <yuyangit.0515@qq.com>
Classifier: Programming Language :: Python :: 3
Requires-Python: >=3.11.3
License-File: LICENSE
Requires-Dist: importlib-resources
Requires-Dist: xy-file
Requires-Dist: xy-settings
Requires-Dist: xy-argparse
